<?xml version="1.0" encoding="utf-8"?>
<Expertise>
  <Content>
    <BridgeMask>5</BridgeMask>
    <POISelection name="主区选取参数">
      <Item>
        <FeatureClassName>AGNP</FeatureClassName>
        <RuleName>省、直辖市行政中心</RuleName>
        <Ratio>1.0</Ratio>
      </Item>
      <Item>
        <FeatureClassName>AGNP</FeatureClassName>
        <RuleName>设区市行政中心</RuleName>
        <Ratio>1.0</Ratio>
      </Item>
      <Item>
        <FeatureClassName>AGNP</FeatureClassName>
        <RuleName>县(区、市)行政中心</RuleName>
        <Ratio>1.0</Ratio>
      </Item>
      <Item>
        <FeatureClassName>AGNP</FeatureClassName>
        <RuleName>乡镇级政府</RuleName>
        <Ratio>0.8</Ratio>
      </Item>
      <Item>
        <FeatureClassName>AGNP</FeatureClassName>
        <RuleName>行政村</RuleName>
        <Ratio>0.6</Ratio>
      </Item>
      <Item>
        <FeatureClassName>AGNP</FeatureClassName>
        <RuleName>自然村</RuleName>
        <Ratio>0.6</Ratio>
      </Item>
      <Item>
        <FeatureClassName>AGNP</FeatureClassName>
        <RuleName>牧点、渔点、棚屋</RuleName>
        <Ratio>0.6</Ratio>
      </Item>
      <Item>
        <FeatureClassName>LFCP</FeatureClassName>
        <RuleName>山峰</RuleName>
        <Ratio>0.6</Ratio>
      </Item>
      <Item>
        <FeatureClassName>LFCP</FeatureClassName>
        <RuleName>收费站（出入口）</RuleName>
        <Ratio>0.6</Ratio>
      </Item>
      <Item>
        <FeatureClassName>AGNP</FeatureClassName>
        <RuleName>国外主要城市</RuleName>
        <Ratio>1</Ratio>
      </Item>
      <Item>
        <FeatureClassName>AGNP</FeatureClassName>
        <RuleName>国外一般城市</RuleName>
        <Ratio>1</Ratio>
      </Item>
    </POISelection>
    <POISelectionEx name="附区选取参数">
      <Item>
        <FeatureClassName>AGNP</FeatureClassName>
        <RuleName>省、直辖市行政中心</RuleName>
        <Ratio>1.0</Ratio>
      </Item>
      <Item>
        <FeatureClassName>AGNP</FeatureClassName>
        <RuleName>设区市行政中心</RuleName>
        <Ratio>1.0</Ratio>
      </Item>
      <Item>
        <FeatureClassName>AGNP</FeatureClassName>
        <RuleName>县(区、市)行政中心</RuleName>
        <Ratio>1.0</Ratio>
      </Item>
      <Item>
        <FeatureClassName>AGNP</FeatureClassName>
        <RuleName>乡镇级政府</RuleName>
        <Ratio>0.4</Ratio>
      </Item>
      <Item>
        <FeatureClassName>AGNP</FeatureClassName>
        <RuleName>行政村</RuleName>
        <Ratio>0.4</Ratio>
      </Item>
      <Item>
        <FeatureClassName>AGNP</FeatureClassName>
        <RuleName>自然村</RuleName>
        <Ratio>0.4</Ratio>
      </Item>
      <Item>
        <FeatureClassName>AGNP</FeatureClassName>
        <RuleName>牧点、渔点、棚屋</RuleName>
        <Ratio>0.4</Ratio>
      </Item>
      <Item>
        <FeatureClassName>LFCP</FeatureClassName>
        <RuleName>山峰</RuleName>
        <Ratio>0.3</Ratio>
      </Item>
      <Item>
        <FeatureClassName>LFCP</FeatureClassName>
        <RuleName>收费站（出入口）</RuleName>
        <Ratio>0.3</Ratio>
      </Item>
      <Item>
        <FeatureClassName>AGNP</FeatureClassName>
        <RuleName>国外主要城市</RuleName>
        <Ratio>1</Ratio>
      </Item>
      <Item>
        <FeatureClassName>AGNP</FeatureClassName>
        <RuleName>国外一般城市</RuleName>
        <Ratio>1</Ratio>
      </Item>
    </POISelectionEx>
    <BoundaryProcess>
      <Province>630201</Province>
      <State>640201</State>
      <County>650201</County>
      <Town>660201</Town>
      <BoundaryLyr>HYDL</BoundaryLyr>
      <BoundaryLyr>LRDL</BoundaryLyr>
      <SolidValue>12.5</SolidValue>
      <BlankValue>15</BlankValue>
      <BufferValue>0</BufferValue>
    </BoundaryProcess>
    <RiverAutoGradual>
      <StartWidth>0.12</StartWidth>
      <EndWidth>0.5</EndWidth>
    </RiverAutoGradual>
    <MapScaleRule>
      <Item>
        <Scale>100000</Scale>
        <Max>150000</Max>
        <Min>70001</Min>
        <DatabaseName>nx10</DatabaseName>
        <MapTemplate>10万</MapTemplate>
      </Item>
    </MapScaleRule>
    <HillShading>
      <Azimuth>315</Azimuth>
      <Altitude>45</Altitude>
      <InModelShadows>0</InModelShadows>
      <ZFactor>1</ZFactor>
    </HillShading>
    <LandForm>
      <Item>
        <MinSlope>0</MinSlope>
        <MaxSlope>2</MaxSlope>
        <Val>1</Val>
        <Name>平原</Name>
      </Item>
      <Item>
        <MinSlope>2</MinSlope>
        <MaxSlope>6</MaxSlope>
        <Val>2</Val>
        <Name>丘陵</Name>
      </Item>
      <Item>
        <MinSlope>6</MinSlope>
        <MaxSlope>25</MaxSlope>
        <Val>3</Val>
        <Name>山地</Name>
      </Item>
      <Item>
        <MinSlope>25</MinSlope>
        <MaxSlope>90</MaxSlope>
        <Val>4</Val>
        <Name>高山地</Name>
      </Item>
    </LandForm>
    <SymbolProcess>
      <FCName>AGNP</FCName>
      <LevelFieldName>class</LevelFieldName>
    </SymbolProcess>
  </Content>
</Expertise>